{
  "book": "Micah",
  "book_number": 33,
  "total_chapters": 7,
  "chapters": [
    {
      "chapter": 1,
      "audio_url": "https://kjv-bible-audio-cdn.netlify.app/ot/33_Micah_01.mp3"
    },
    {
      "chapter": 2,
      "audio_url": "https://kjv-bible-audio-cdn.netlify.app/ot/33_Micah_02.mp3"
    },
    {
      "chapter": 3,
      "audio_url": "https://kjv-bible-audio-cdn.netlify.app/ot/33_Micah_03.mp3"
    },
    {
      "chapter": 4,
      "audio_url": "https://kjv-bible-audio-cdn.netlify.app/ot/33_Micah_04.mp3"
    },
    {
      "chapter": 5,
      "audio_url": "https://kjv-bible-audio-cdn.netlify.app/ot/33_Micah_05.mp3"
    },
    {
      "chapter": 6,
      "audio_url": "https://kjv-bible-audio-cdn.netlify.app/ot/33_Micah_06.mp3"
    },
    {
      "chapter": 7,
      "audio_url": "https://kjv-bible-audio-cdn.netlify.app/ot/33_Micah_07.mp3"
    }
  ]
}